
<?xml version="1.0" encoding="UTF-8"?>
<theme>
   <formatVersion>7</formatVersion>
   

   <view name="grid">

    <video name="md_video">
		<visible>false</visible>
	</video>
	  
	<text name="md_genre">
			<size>0.83 0.19</size>
			<color>ffffff</color> <origin>0.5 0.5</origin>
			<pos>0.47 0.820</pos>
			<fontSize>0.04</fontSize>
			<fontPath>./_inc/fonts/gomarice_no_continue.ttf</fontPath>
			<zIndex>91</zIndex>  
		</text>
		
	<text name="md_description">
	  	<color>ffffff</color>
		<fontSize>0.024</fontSize>
		<fontPath>./_inc/fonts/gomarice_no_continue.ttf</fontPath>
		<size>0.20 0.10</size>
		<pos>0.08 0.860</pos>
    </text>

	<text name="md_name">
			<fontPath>./_inc/fonts/gomarice_no_continue.ttf</fontPath>
			<fontSize>0.04</fontSize>
			<pos>0.05 0.05</pos>
			<size>0.6875 0.0248148148148148</size>
			<alignment>left</alignment>
			<color>ffffff</color>
		</text>
	
	<image name="md_marquee">
			<origin>1 0.5</origin>
			<pos>0.95 0.052</pos>
			<maxSize>0.2 0.08</maxSize>
		</image>
	
	 <helpsystem name="help">
         <fontPath>./_inc/fonts/gomarice_no_continue.ttf</fontPath>
         <fontSize>0.0215</fontSize>      
         <pos>0.30 0.942</pos>      
         <textColor>ffffff</textColor>
         <iconColor>ffffff</iconColor>
      </helpsystem>
	
		<gridtile name="default">
			<size>0.22875 0.33</size>
			<backgroundColor>00000000</backgroundColor>
		</gridtile>
	
	 <image name="background" extra="true">
         <origin>0 0</origin>
         <path>./_inc/teste.jpg</path>
         <pos>0 0</pos>
         <size>1 1</size>
		 <zIndex>8</zIndex>    
      </image>
	
	 <image name="line1" extra="true">
         <origin>0.5 1</origin>
         <path>./_inc/white.png</path>
         <pos>0.5 0.105</pos>
         <size>1 0.003</size>
		 <zIndex>500</zIndex>    
      </image>

	  	 <image name="line2" extra="true">
         <origin>0.5 0</origin>
         <path>./_inc/white.png</path>
         <pos>0.5 0.775</pos>
         <size>1 0.003</size>
		 <zIndex>500</zIndex>    
      </image>
	  
    <imagegrid name="gamegrid">
		<color>000000</color>
		<pos>0 0.105</pos>
		<size>1 0.67</size>
		<autoLayout>5 3</autoLayout>
		<margin>0 0</margin>
		<padding>0.05 0 0.05 0</padding>
		<autoLayoutSelectedZoom>1</autoLayoutSelectedZoom>
		<animateSelection>false</animateSelection>
		<imageSource>image</imageSource>				
        <zIndex>300</zIndex>
		<showVideoAtDelay>600</showVideoAtDelay>
    </imagegrid>
	
    <image name="gridtile.image">
      <roundCorners>0.06</roundCorners>
    </image>
	
    <gridtile name="default">
      <imageSizeMode>minSize</imageSizeMode>	
      <backgroundColor>00000000</backgroundColor>
      <backgroundCornerSize>0.06</backgroundCornerSize>
      <selectionMode>video</selectionMode>
      <padding>5 5</padding>
      <imageColor>606060</imageColor>
      <reflexion>0.25 0.0</reflexion>
    </gridtile>
	
    <gridtile name="selected">
      <backgroundCenterColor>00000000</backgroundCenterColor>
      <backgroundEdgeColor>00ff00</backgroundEdgeColor>	
      <imageColor>FFFFFFFF</imageColor>
    </gridtile>

    <ninepatch name="gridtile.background:selected">
      <animateColor>ff0000</animateColor>
      <animateColorTime>75</animateColorTime>
    </ninepatch>

   <image name="gridtile.marquee">
      <origin>0.5 0.5</origin>
      <pos>0.5 0.5</pos>
      <color>FFFFFFFF</color>
      <size>0.96 0.96</size>
    </image>
	
    <image name="gridtile.marquee:selected">
      <origin>0 0</origin>
      <pos>0.05 0.01</pos>
      <color>ffffff</color>
      <size>0.96 0.1</size>
    </image>

    <image name="gridtile.marquee:videoplaying">
	  <origin>0 0</origin>
      <pos>0.05 0.01</pos>
      <color>ffffff00</color>
      <size>0.96 0.10</size>
	  </image>
	
</view>

	
</theme>
